{"quote":"Mga minamahal, huwag ninyong paniniwalaan kaagad ang bawat nagsasabing nasa kanila ang Espiritu. Sa halip, subukin muna ninyo sila upang malaman kung talagang mula sa Diyos ang espiritung nasa kanila, sapagkat marami nang huwad na propeta sa mundong ito. Ito ang palatandaan na ang Espiritu ng Diyos nga ang nasa kanila: kung ipinapahayag nila na si Jesu-Cristo ay naging tao. Kung hindi gayon ang kanilang ipinapahayag tungkol kay Jesus, hindi mula sa Diyos ang espiritung nasa kanila. Ang espiritu ng anti-Cristo ang nasa kanila. Nasabi na sa inyong ito\u0027y darating at ngayon nga\u0027y nasa daigdig na.","verse":"1 Juan 4:1-3 MBB05","language":"Tagalog","fileName":"1Juan4_1-3MBB05","fileType":"scripture_quote","fileDescription":"1 Juan 4:1-3 MBB05","category":"tagalog","tags":["anti-cristo"]}