{"quote":"Ako\u0027y naging lingkod nito nang piliin ako ng Diyos upang ipahayag sa inyo ang kanyang salita, ang hiwaga na sa mahabang panahon ay inilihim sa maraming sali\u0027t saling lahi, ngunit ngayo\u0027y inihayag na sa kanyang mga pinili. Niloob ng Diyos na ihayag sa lahat ng mga Hentil ang dakila at kamangha-manghang hiwagang ito na walang iba kundi si Cristo na nasa inyo. Siya ang ating pag-asa na tayo\u0027y makakabahagi sa kaluwalhatian ng Diyos.","verse":"Colosas 1:25-27 MBB05","language":"Tagalog","fileName":"Colosas1_25-27MBB05","fileType":"scripture_quote","fileDescription":"Colosas 1:25-27 MBB05","category":"tagalog","tags":["salita","lingkod","hiwaga","cristo"]}